projetotn/__init__.py
projetotn/__main__.py
projetotn/appromo.py
projetotn/funcao.py
projetotn/pilar2.py
projetotn-1.1.9.dist-info/METADATA
projetotn-1.1.9.dist-info/WHEEL
projetotn-1.1.9.dist-info/top_level.txt
projetotn-1.1.9.dist-info/RECORD
