Metadata-Version: 2.1
Name: projetotn
Version: 1.1.9
Summary: Atualizamos a lista das chars (NÃO APLICA)
Home-page: https://medium.com/jeiso-silva
Author: Jeiso Silva
Author-email: jeiso.ps@outlook.com
License: MIT
Keywords: Testing
Platform: UNKNOWN
Classifier: Development Status :: 3 - Alpha
Classifier: Intended Audience :: Developers
Classifier: Topic :: Education :: Testing
Classifier: License :: OSI Approved :: MIT License
Classifier: Programming Language :: Python :: 3
Classifier: Programming Language :: Python :: 3.2
Classifier: Programming Language :: Python :: 3.3
Classifier: Programming Language :: Python :: 3.4
Classifier: Programming Language :: Python :: 3.5
Classifier: Programming Language :: Python :: 3.6
Classifier: Programming Language :: Python :: 3.7
Requires-Dist: sh (>=1.11)
